{
  "package_schema_version": "1.2.0",
  "name": "complex_dep_pkg",
  "version": "1.1.0",
  "description": "Package with multiple dependencies for testing",
  "tags": ["test", "dependency", "complex"],
  "author": {
    "name": "Test User",
    "email": "test@example.com"
  },
  "license": {
    "name": "MIT"
  },
  "entry_point": "server.py",
  "tools": [
    {"name": "complex_function", "description": "Complex function that depends on both base packages"}
  ],
  "dependencies": {
    "hatch": [
      {"name": "base_pkg_1", "version_constraint": ">=1.0.0"},
      {"name": "base_pkg_2", "version_constraint": ">=1.0.0"}
    ],
    "python": [],
    "system": [],
    "docker": []
  },
  "citations": {
    "origin": "Complex dependency package for testing",
    "mcp": "Complex dependency package MCP implementation"
  }
}
